domtree/__init__.py
domtree/node.py
domtree/svg.py
domtree/svg_stubs.py
domtree/test.py
domtree-0.0.5.dist-info/LICENSE
domtree-0.0.5.dist-info/METADATA
domtree-0.0.5.dist-info/WHEEL
domtree-0.0.5.dist-info/top_level.txt
domtree-0.0.5.dist-info/RECORD
