Metadata-Version: 2.1
Name: domtree
Version: 0.0.5
Summary: DOM Tree syntax for python
License: Apache License
Requires-Python: >=3.7
License-File: LICENSE
Requires-Dist: typing-extensions (>4)
Provides-Extra: test
Requires-Dist: pytest ; extra == 'test'
